pysparksqlt/__init__.py
pysparksqlt/main.py
pysparksqlt-0.1.0.dist-info/METADATA
pysparksqlt-0.1.0.dist-info/WHEEL
pysparksqlt-0.1.0.dist-info/top_level.txt
pysparksqlt-0.1.0.dist-info/RECORD
